hypermodern/__init__.py
hypermodern/console.py
hypermodern/wikipedia.py
hypermodern-0.1.0.dist-info/entry_points.txt
hypermodern-0.1.0.dist-info/METADATA
hypermodern-0.1.0.dist-info/LICENSE
hypermodern-0.1.0.dist-info/WHEEL
hypermodern-0.1.0.dist-info/RECORD
