Metadata-Version: 2.1
Name: hypermodern
Version: 0.1.0
Summary: 
License: MIT
Author: Kevin Riley
Author-email: kevin@redcode.works
Requires-Python: >=3.11,<4.0
Classifier: License :: OSI Approved :: MIT License
Classifier: Programming Language :: Python :: 3
Classifier: Programming Language :: Python :: 3.11
Requires-Dist: SQLAlchemy (>=1.4.45,<2.0.0)
Requires-Dist: cleo (>=2.0.1,<3.0.0)
Requires-Dist: click (>=8.0.4,<9.0.0)
Requires-Dist: csvkit (>=1.0.7,<2.0.0)
Requires-Dist: desert (>=2022.9.22,<2023.0.0)
Requires-Dist: httpx (>=0.23.1,<0.24.0)
Requires-Dist: isort (>=5.11.4,<6.0.0)
Requires-Dist: marshmallow (>=3.19.0,<4.0.0)
Requires-Dist: mypy (>=0.991,<0.992)
Requires-Dist: requests (>=2.28.1,<3.0.0)
Requires-Dist: typer (>=0.7.0,<0.8.0)
Requires-Dist: types-requests (>=2.28.11.7,<3.0.0.0)
